phylics/__init__.py
phylics/_compat.py
phylics/_settings.py
phylics/check_funcs.py
phylics/constants.py
phylics/drawer.py
phylics/logging.py
phylics/tools.py
phylics/utils.py
phylics/clustering/CN.py
phylics/clustering/Gen_Ref_Fa.py
phylics/clustering/TreeCluster.py
phylics/clustering/__init__.py
phylics/clustering/affinity.py
phylics/clustering/agglomerative.py
phylics/clustering/apn_stats.py
phylics/clustering/birch.py
phylics/clustering/cl_external_validation.py
phylics/clustering/cl_stability.py
phylics/clustering/cl_validity.py
phylics/clustering/clust_manual.py
phylics/clustering/cluster.py
phylics/clustering/cluster_heatmap.py
phylics/clustering/cluster_heatmap_pca.py
phylics/clustering/clustering_old.py
phylics/clustering/connectivity_stats.py
phylics/clustering/consensus_clustering.py
phylics/clustering/consensus_clustering_k.py
phylics/clustering/coph_aff_stats.py
phylics/clustering/cophenetic_affinity.py
phylics/clustering/db_cophenetic_validation.py
phylics/clustering/dbscan.py
phylics/clustering/density_valid_stats.py
phylics/clustering/dunn_stats.py
phylics/clustering/fast_density_based_cl_validity.py
phylics/clustering/gaussian.py
phylics/clustering/gen_tree.py
phylics/clustering/hdbscan_.py
phylics/clustering/heatmap.py
phylics/clustering/hierarchical_manual.py
phylics/clustering/json_to_newick.py
phylics/clustering/kmeans.py
phylics/clustering/make_ginkgo_beds.py
phylics/clustering/make_segcopy.py
phylics/clustering/merge_all.py
phylics/clustering/merge_clustering_stats.py
phylics/clustering/metrics.py
phylics/clustering/mk_dot.py
phylics/clustering/n_clusters_stats.py
phylics/clustering/newick_to_mat.py
phylics/clustering/plot_aggl_heatmap.py
phylics/clustering/plot_aggl_heatmap_pca.py
phylics/clustering/plot_newick_clusters.py
phylics/clustering/plot_newick_heatmap.py
phylics/clustering/preproc.py
phylics/clustering/preproc_umap.py
phylics/clustering/rank_algorithms.py
phylics/clustering/sep_ground_truth.py
phylics/clustering/silhouette_stats.py
phylics-1.0.7.dist-info/METADATA
phylics-1.0.7.dist-info/WHEEL
phylics-1.0.7.dist-info/top_level.txt
phylics-1.0.7.dist-info/RECORD
